ui/README.md
ui/__init__.py
ui/api.py
ui/index.html
ui/run_ui.py
containerized_strands_agents/__init__.py
containerized_strands_agents/agent.py
containerized_strands_agents/agent_manager.py
containerized_strands_agents/cli.py
containerized_strands_agents/config.py
containerized_strands_agents/server.py
containerized_strands_agents/docker/Dockerfile
containerized_strands_agents/docker/agent_runner.py
containerized_strands_agents/docker/github_tools.py
containerized_strands_agents/docker/requirements.txt
containerized_strands_agents/templates/gha-agent-workflow.yml
containerized_strands_agents-0.1.0.dist-info/METADATA
containerized_strands_agents-0.1.0.dist-info/WHEEL
containerized_strands_agents-0.1.0.dist-info/entry_points.txt
containerized_strands_agents-0.1.0.dist-info/licenses/LICENSE
containerized_strands_agents-0.1.0.dist-info/RECORD
