Metadata-Version: 2.4
Name: containerized-strands-agents
Version: 0.1.0
Summary: MCP server that hosts isolated Strands AI agents in Docker containers
Project-URL: Homepage, https://github.com/mkmeral/containerized-strands-agents
Project-URL: Repository, https://github.com/mkmeral/containerized-strands-agents
Project-URL: Documentation, https://github.com/mkmeral/containerized-strands-agents#readme
Project-URL: Issues, https://github.com/mkmeral/containerized-strands-agents/issues
Author-email: Murat Kaan Meral <muratkaanmeral@gmail.com>
License: MIT
License-File: LICENSE
Keywords: agents,ai,bedrock,claude,docker,llm,mcp,strands
Classifier: Development Status :: 4 - Beta
Classifier: Intended Audience :: Developers
Classifier: License :: OSI Approved :: MIT License
Classifier: Operating System :: OS Independent
Classifier: Programming Language :: Python :: 3
Classifier: Programming Language :: Python :: 3.11
Classifier: Programming Language :: Python :: 3.12
Classifier: Programming Language :: Python :: 3.13
Classifier: Topic :: Scientific/Engineering :: Artificial Intelligence
Classifier: Topic :: Software Development :: Libraries :: Python Modules
Requires-Python: >=3.11
Requires-Dist: docker>=7.0.0
Requires-Dist: fastmcp>=2.0.0
Requires-Dist: httpx>=0.27.0
Requires-Dist: pydantic>=2.0.0
Requires-Dist: strands-agents-tools>=0.1.0
Requires-Dist: strands-agents>=0.1.0
Provides-Extra: all
Requires-Dist: fastapi>=0.109.0; extra == 'all'
Requires-Dist: pytest-asyncio>=0.23.0; extra == 'all'
Requires-Dist: pytest>=8.0.0; extra == 'all'
Requires-Dist: uvicorn>=0.27.0; extra == 'all'
Provides-Extra: dev
Requires-Dist: pytest-asyncio>=0.23.0; extra == 'dev'
Requires-Dist: pytest>=8.0.0; extra == 'dev'
Provides-Extra: webui
Requires-Dist: fastapi>=0.109.0; extra == 'webui'
Requires-Dist: uvicorn>=0.27.0; extra == 'webui'
